laura/__init__.py
laura/laura.py
laura/tests/__init__.py
laura/tests/tests.py
laura-0.0.2.dist-info/LICENSE
laura-0.0.2.dist-info/METADATA
laura-0.0.2.dist-info/WHEEL
laura-0.0.2.dist-info/top_level.txt
laura-0.0.2.dist-info/RECORD
