Metadata-Version: 2.1
Name: laura
Version: 0.0.2
Summary: **laura**: Local Auto-Regressive Average
Home-page: https://github.com/LukeTheHecker/laura
Author: Lukas Hecker
Author-email: lukas_hecker@web.de
Classifier: Programming Language :: Python :: 3
Classifier: License :: OSI Approved :: MIT License
Classifier: Operating System :: OS Independent
Requires-Python: >=3.6.0
License-File: LICENSE
Requires-Dist: numpy
Requires-Dist: mne
Requires-Dist: scipy
